dash_component_unload
