Metadata-Version: 1.1
Name: dash-component-unload
Version: 0.0.2
Summary: Simple dash component to listen on unload event
Home-page: https://github.com/ignacioreyna/dash-component-unload.git
Author: Ignacio Reyna <iganre@gmail.com>
Author-email: UNKNOWN
License: MIT
Platform: UNKNOWN
Classifier: Framework :: Dash
